pushjack/__init__.py
pushjack/__version__.py
pushjack/_compat.py
pushjack/apns.py
pushjack/exceptions.py
pushjack/gcm.py
pushjack/utils.py
pushjack-1.6.0.dist-info/AUTHORS.rst
pushjack-1.6.0.dist-info/LICENSE.rst
pushjack-1.6.0.dist-info/METADATA
pushjack-1.6.0.dist-info/WHEEL
pushjack-1.6.0.dist-info/top_level.txt
pushjack-1.6.0.dist-info/RECORD
